[
    {
        "id": "bahrain",
        "round": "1",
        "location": {
            "country": "Bahrain",
            "city": "Sakhir"
        },
        "circuit_name": "Bahrain International Circuit",
        "date": "02.03.2024"
    },
    {
        "id": "jeddah",
        "round": "2",
        "location": {
            "country": "Saudi Arabia",
            "city": "Jeddah"
        },
        "circuit_name": "Jeddah Corniche Circuit",
        "date": "09.03.2024"
    },
    {
        "id": "albert_park",
        "round": "3",
        "location": {
            "country": "Australia",
            "city": "Melbourne"
        },
        "circuit_name": "Albert Park Grand Prix Circuit",
        "date": "24.03.2024"
    },
    {
        "id": "suzuka",
        "round": "4",
        "location": {
            "country": "Japan",
            "city": "Suzuka"
        },
        "circuit_name": "Suzuka Circuit",
        "date": "07.04.2024"
    },
    {
        "id": "shanghai",
        "round": "5",
        "location": {
            "country": "China",
            "city": "Shanghai"
        },
        "circuit_name": "Shanghai International Circuit",
        "date": "21.04.2024"
    },
    {
        "id": "miami",
        "round": "6",
        "location": {
            "country": "USA",
            "city": "Miami"
        },
        "circuit_name": "Miami International Autodrome",
        "date": "05.05.2024"
    },
    {
        "id": "imola",
        "round": "7",
        "location": {
            "country": "Italy",
            "city": "Imola"
        },
        "circuit_name": "Autodromo Enzo e Dino Ferrari",
        "date": "19.05.2024"
    },
    {
        "id": "monaco",
        "round": "8",
        "location": {
            "country": "Monaco",
            "city": "Monte-Carlo"
        },
        "circuit_name": "Circuit de Monaco",
        "date": "26.05.2024"
    },
    {
        "id": "villeneuve",
        "round": "9",
        "location": {
            "country": "Canada",
            "city": "Montreal"
        },
        "circuit_name": "Circuit Gilles Villeneuve",
        "date": "09.06.2024"
    },
    {
        "id": "catalunya",
        "round": "10",
        "location": {
            "country": "Spain",
            "city": "Montmeló"
        },
        "circuit_name": "Circuit de Barcelona-Catalunya",
        "date": "23.06.2024"
    },
    {
        "id": "red_bull_ring",
        "round": "11",
        "location": {
            "country": "Austria",
            "city": "Spielberg"
        },
        "circuit_name": "Red Bull Ring",
        "date": "30.06.2024"
    },
    {
        "id": "silverstone",
        "round": "12",
        "location": {
            "country": "UK",
            "city": "Silverstone"
        },
        "circuit_name": "Silverstone Circuit",
        "date": "07.07.2024"
    },
    {
        "id": "hungaroring",
        "round": "13",
        "location": {
            "country": "Hungary",
            "city": "Budapest"
        },
        "circuit_name": "Hungaroring",
        "date": "21.07.2024"
    },
    {
        "id": "spa",
        "round": "14",
        "location": {
            "country": "Belgium",
            "city": "Spa"
        },
        "circuit_name": "Circuit de Spa-Francorchamps",
        "date": "28.07.2024"
    },
    {
        "id": "zandvoort",
        "round": "15",
        "location": {
            "country": "Netherlands",
            "city": "Zandvoort"
        },
        "circuit_name": "Circuit Park Zandvoort",
        "date": "25.08.2024"
    },
    {
        "id": "monza",
        "round": "16",
        "location": {
            "country": "Italy",
            "city": "Monza"
        },
        "circuit_name": "Autodromo Nazionale di Monza",
        "date": "01.09.2024"
    },
    {
        "id": "baku",
        "round": "17",
        "location": {
            "country": "Azerbaijan",
            "city": "Baku"
        },
        "circuit_name": "Baku City Circuit",
        "date": "15.09.2024"
    },
    {
        "id": "marina_bay",
        "round": "18",
        "location": {
            "country": "Singapore",
            "city": "Marina Bay"
        },
        "circuit_name": "Marina Bay Street Circuit",
        "date": "22.09.2024"
    },
    {
        "id": "americas",
        "round": "19",
        "location": {
            "country": "USA",
            "city": "Austin"
        },
        "circuit_name": "Circuit of the Americas",
        "date": "20.10.2024"
    },
    {
        "id": "rodriguez",
        "round": "20",
        "location": {
            "country": "Mexico",
            "city": "Mexico City"
        },
        "circuit_name": "Autódromo Hermanos Rodríguez",
        "date": "27.10.2024"
    },
    {
        "id": "interlagos",
        "round": "21",
        "location": {
            "country": "Brazil",
            "city": "São Paulo"
        },
        "circuit_name": "Autódromo José Carlos Pace",
        "date": "03.11.2024"
    },
    {
        "id": "vegas",
        "round": "22",
        "location": {
            "country": "United States",
            "city": "Las Vegas"
        },
        "circuit_name": "Las Vegas Strip Street Circuit",
        "date": "23.11.2024"
    },
    {
        "id": "losail",
        "round": "23",
        "location": {
            "country": "Qatar",
            "city": "Al Daayen"
        },
        "circuit_name": "Losail International Circuit",
        "date": "01.12.2024"
    },
    {
        "id": "yas_marina",
        "round": "24",
        "location": {
            "country": "UAE",
            "city": "Abu Dhabi"
        },
        "circuit_name": "Yas Marina Circuit",
        "date": "08.12.2024"
    }
]