{
    "1": [
        {
            "position": "1",
            "constructor": "mercedes",
            "name": "Mercedes"
        },
        {
            "position": "2",
            "constructor": "mclaren",
            "name": "McLaren"
        },
        {
            "position": "3",
            "constructor": "ferrari",
            "name": "Ferrari"
        },
        {
            "position": "4",
            "constructor": "alphatauri",
            "name": "AlphaTauri"
        },
        {
            "position": "5",
            "constructor": "renault",
            "name": "Renault"
        },
        {
            "position": "6",
            "constructor": "alfa",
            "name": "Alfa Romeo"
        },
        {
            "position": "7",
            "constructor": "racing_point",
            "name": "Racing Point"
        },
        {
            "position": "8",
            "constructor": "williams",
            "name": "Williams"
        },
        {
            "position": "9",
            "constructor": "red_bull",
            "name": "Red Bull"
        },
        {
            "position": null,
            "constructor": "haas",
            "name": "Haas F1 Team"
        }
    ],
    "2": [
        {
            "position": "1",
            "constructor": "mercedes",
            "name": "Mercedes"
        },
        {
            "position": "2",
            "constructor": "mclaren",
            "name": "McLaren"
        },
        {
            "position": "3",
            "constructor": "red_bull",
            "name": "Red Bull"
        },
        {
            "position": "4",
            "constructor": "ferrari",
            "name": "Ferrari"
        },
        {
            "position": "5",
            "constructor": "renault",
            "name": "Renault"
        },
        {
            "position": "6",
            "constructor": "racing_point",
            "name": "Racing Point"
        },
        {
            "position": "7",
            "constructor": "alphatauri",
            "name": "AlphaTauri"
        },
        {
            "position": "8",
            "constructor": "alfa",
            "name": "Alfa Romeo"
        },
        {
            "position": "9",
            "constructor": "williams",
            "name": "Williams"
        },
        {
            "position": "10",
            "constructor": "haas",
            "name": "Haas F1 Team"
        }
    ],
    "3": [
        {
            "position": "1",
            "constructor": "mercedes",
            "name": "Mercedes"
        },
        {
            "position": "2",
            "constructor": "red_bull",
            "name": "Red Bull"
        },
        {
            "position": "3",
            "constructor": "mclaren",
            "name": "McLaren"
        },
        {
            "position": "4",
            "constructor": "ferrari",
            "name": "Ferrari"
        },
        {
            "position": "5",
            "constructor": "racing_point",
            "name": "Racing Point"
        },
        {
            "position": "6",
            "constructor": "renault",
            "name": "Renault"
        },
        {
            "position": "7",
            "constructor": "alphatauri",
            "name": "AlphaTauri"
        },
        {
            "position": "8",
            "constructor": "alfa",
            "name": "Alfa Romeo"
        },
        {
            "position": "9",
            "constructor": "haas",
            "name": "Haas F1 Team"
        },
        {
            "position": "10",
            "constructor": "williams",
            "name": "Williams"
        }
    ],
    "4": [
        {
            "position": "1",
            "constructor": "mercedes",
            "name": "Mercedes"
        },
        {
            "position": "2",
            "constructor": "red_bull",
            "name": "Red Bull"
        },
        {
            "position": "3",
            "constructor": "mclaren",
            "name": "McLaren"
        },
        {
            "position": "4",
            "constructor": "ferrari",
            "name": "Ferrari"
        },
        {
            "position": "5",
            "constructor": "renault",
            "name": "Renault"
        },
        {
            "position": "6",
            "constructor": "racing_point",
            "name": "Racing Point"
        },
        {
            "position": "7",
            "constructor": "alphatauri",
            "name": "AlphaTauri"
        },
        {
            "position": "8",
            "constructor": "alfa",
            "name": "Alfa Romeo"
        },
        {
            "position": "9",
            "constructor": "haas",
            "name": "Haas F1 Team"
        },
        {
            "position": "10",
            "constructor": "williams",
            "name": "Williams"
        }
    ],
    "5": [
        {
            "position": "1",
            "constructor": "mercedes",
            "name": "Mercedes"
        },
        {
            "position": "2",
            "constructor": "red_bull",
            "name": "Red Bull"
        },
        {
            "position": "3",
            "constructor": "ferrari",
            "name": "Ferrari"
        },
        {
            "position": "4",
            "constructor": "mclaren",
            "name": "McLaren"
        },
        {
            "position": "5",
            "constructor": "racing_point",
            "name": "Racing Point"
        },
        {
            "position": "6",
            "constructor": "renault",
            "name": "Renault"
        },
        {
            "position": "7",
            "constructor": "alphatauri",
            "name": "AlphaTauri"
        },
        {
            "position": "8",
            "constructor": "alfa",
            "name": "Alfa Romeo"
        },
        {
            "position": "9",
            "constructor": "haas",
            "name": "Haas F1 Team"
        },
        {
            "position": "10",
            "constructor": "williams",
            "name": "Williams"
        }
    ],
    "6": [
        {
            "position": "1",
            "constructor": "mercedes",
            "name": "Mercedes"
        },
        {
            "position": "2",
            "constructor": "red_bull",
            "name": "Red Bull"
        },
        {
            "position": "3",
            "constructor": "racing_point",
            "name": "Racing Point"
        },
        {
            "position": "4",
            "constructor": "mclaren",
            "name": "McLaren"
        },
        {
            "position": "5",
            "constructor": "ferrari",
            "name": "Ferrari"
        },
        {
            "position": "6",
            "constructor": "renault",
            "name": "Renault"
        },
        {
            "position": "7",
            "constructor": "alphatauri",
            "name": "AlphaTauri"
        },
        {
            "position": "8",
            "constructor": "alfa",
            "name": "Alfa Romeo"
        },
        {
            "position": "9",
            "constructor": "haas",
            "name": "Haas F1 Team"
        },
        {
            "position": "10",
            "constructor": "williams",
            "name": "Williams"
        }
    ],
    "7": [
        {
            "position": "1",
            "constructor": "mercedes",
            "name": "Mercedes"
        },
        {
            "position": "2",
            "constructor": "red_bull",
            "name": "Red Bull"
        },
        {
            "position": "3",
            "constructor": "mclaren",
            "name": "McLaren"
        },
        {
            "position": "4",
            "constructor": "racing_point",
            "name": "Racing Point"
        },
        {
            "position": "5",
            "constructor": "ferrari",
            "name": "Ferrari"
        },
        {
            "position": "6",
            "constructor": "renault",
            "name": "Renault"
        },
        {
            "position": "7",
            "constructor": "alphatauri",
            "name": "AlphaTauri"
        },
        {
            "position": "8",
            "constructor": "alfa",
            "name": "Alfa Romeo"
        },
        {
            "position": "9",
            "constructor": "haas",
            "name": "Haas F1 Team"
        },
        {
            "position": "10",
            "constructor": "williams",
            "name": "Williams"
        }
    ],
    "8": [
        {
            "position": "1",
            "constructor": "mercedes",
            "name": "Mercedes"
        },
        {
            "position": "2",
            "constructor": "red_bull",
            "name": "Red Bull"
        },
        {
            "position": "3",
            "constructor": "mclaren",
            "name": "McLaren"
        },
        {
            "position": "4",
            "constructor": "racing_point",
            "name": "Racing Point"
        },
        {
            "position": "5",
            "constructor": "renault",
            "name": "Renault"
        },
        {
            "position": "6",
            "constructor": "ferrari",
            "name": "Ferrari"
        },
        {
            "position": "7",
            "constructor": "alphatauri",
            "name": "AlphaTauri"
        },
        {
            "position": "8",
            "constructor": "alfa",
            "name": "Alfa Romeo"
        },
        {
            "position": "9",
            "constructor": "haas",
            "name": "Haas F1 Team"
        },
        {
            "position": "10",
            "constructor": "williams",
            "name": "Williams"
        }
    ],
    "9": [
        {
            "position": "1",
            "constructor": "mercedes",
            "name": "Mercedes"
        },
        {
            "position": "2",
            "constructor": "red_bull",
            "name": "Red Bull"
        },
        {
            "position": "3",
            "constructor": "mclaren",
            "name": "McLaren"
        },
        {
            "position": "4",
            "constructor": "racing_point",
            "name": "Racing Point"
        },
        {
            "position": "5",
            "constructor": "renault",
            "name": "Renault"
        },
        {
            "position": "6",
            "constructor": "ferrari",
            "name": "Ferrari"
        },
        {
            "position": "7",
            "constructor": "alphatauri",
            "name": "AlphaTauri"
        },
        {
            "position": "8",
            "constructor": "alfa",
            "name": "Alfa Romeo"
        },
        {
            "position": "9",
            "constructor": "haas",
            "name": "Haas F1 Team"
        },
        {
            "position": "10",
            "constructor": "williams",
            "name": "Williams"
        }
    ],
    "10": [
        {
            "position": "1",
            "constructor": "mercedes",
            "name": "Mercedes"
        },
        {
            "position": "2",
            "constructor": "red_bull",
            "name": "Red Bull"
        },
        {
            "position": "3",
            "constructor": "mclaren",
            "name": "McLaren"
        },
        {
            "position": "4",
            "constructor": "racing_point",
            "name": "Racing Point"
        },
        {
            "position": "5",
            "constructor": "renault",
            "name": "Renault"
        },
        {
            "position": "6",
            "constructor": "ferrari",
            "name": "Ferrari"
        },
        {
            "position": "7",
            "constructor": "alphatauri",
            "name": "AlphaTauri"
        },
        {
            "position": "8",
            "constructor": "alfa",
            "name": "Alfa Romeo"
        },
        {
            "position": "9",
            "constructor": "haas",
            "name": "Haas F1 Team"
        },
        {
            "position": "10",
            "constructor": "williams",
            "name": "Williams"
        }
    ],
    "11": [
        {
            "position": "1",
            "constructor": "mercedes",
            "name": "Mercedes"
        },
        {
            "position": "2",
            "constructor": "red_bull",
            "name": "Red Bull"
        },
        {
            "position": "3",
            "constructor": "racing_point",
            "name": "Racing Point"
        },
        {
            "position": "4",
            "constructor": "mclaren",
            "name": "McLaren"
        },
        {
            "position": "5",
            "constructor": "renault",
            "name": "Renault"
        },
        {
            "position": "6",
            "constructor": "ferrari",
            "name": "Ferrari"
        },
        {
            "position": "7",
            "constructor": "alphatauri",
            "name": "AlphaTauri"
        },
        {
            "position": "8",
            "constructor": "alfa",
            "name": "Alfa Romeo"
        },
        {
            "position": "9",
            "constructor": "haas",
            "name": "Haas F1 Team"
        },
        {
            "position": "10",
            "constructor": "williams",
            "name": "Williams"
        }
    ],
    "12": [
        {
            "position": "1",
            "constructor": "mercedes",
            "name": "Mercedes"
        },
        {
            "position": "2",
            "constructor": "red_bull",
            "name": "Red Bull"
        },
        {
            "position": "3",
            "constructor": "racing_point",
            "name": "Racing Point"
        },
        {
            "position": "4",
            "constructor": "mclaren",
            "name": "McLaren"
        },
        {
            "position": "5",
            "constructor": "renault",
            "name": "Renault"
        },
        {
            "position": "6",
            "constructor": "ferrari",
            "name": "Ferrari"
        },
        {
            "position": "7",
            "constructor": "alphatauri",
            "name": "AlphaTauri"
        },
        {
            "position": "8",
            "constructor": "alfa",
            "name": "Alfa Romeo"
        },
        {
            "position": "9",
            "constructor": "haas",
            "name": "Haas F1 Team"
        },
        {
            "position": "10",
            "constructor": "williams",
            "name": "Williams"
        }
    ],
    "13": [
        {
            "position": "1",
            "constructor": "mercedes",
            "name": "Mercedes"
        },
        {
            "position": "2",
            "constructor": "red_bull",
            "name": "Red Bull"
        },
        {
            "position": "3",
            "constructor": "renault",
            "name": "Renault"
        },
        {
            "position": "4",
            "constructor": "mclaren",
            "name": "McLaren"
        },
        {
            "position": "5",
            "constructor": "racing_point",
            "name": "Racing Point"
        },
        {
            "position": "6",
            "constructor": "ferrari",
            "name": "Ferrari"
        },
        {
            "position": "7",
            "constructor": "alphatauri",
            "name": "AlphaTauri"
        },
        {
            "position": "8",
            "constructor": "alfa",
            "name": "Alfa Romeo"
        },
        {
            "position": "9",
            "constructor": "haas",
            "name": "Haas F1 Team"
        },
        {
            "position": "10",
            "constructor": "williams",
            "name": "Williams"
        }
    ],
    "14": [
        {
            "position": "1",
            "constructor": "mercedes",
            "name": "Mercedes"
        },
        {
            "position": "2",
            "constructor": "red_bull",
            "name": "Red Bull"
        },
        {
            "position": "3",
            "constructor": "racing_point",
            "name": "Racing Point"
        },
        {
            "position": "4",
            "constructor": "mclaren",
            "name": "McLaren"
        },
        {
            "position": "5",
            "constructor": "renault",
            "name": "Renault"
        },
        {
            "position": "6",
            "constructor": "ferrari",
            "name": "Ferrari"
        },
        {
            "position": "7",
            "constructor": "alphatauri",
            "name": "AlphaTauri"
        },
        {
            "position": "8",
            "constructor": "alfa",
            "name": "Alfa Romeo"
        },
        {
            "position": "9",
            "constructor": "haas",
            "name": "Haas F1 Team"
        },
        {
            "position": "10",
            "constructor": "williams",
            "name": "Williams"
        }
    ],
    "15": [
        {
            "position": "1",
            "constructor": "mercedes",
            "name": "Mercedes"
        },
        {
            "position": "2",
            "constructor": "red_bull",
            "name": "Red Bull"
        },
        {
            "position": "3",
            "constructor": "mclaren",
            "name": "McLaren"
        },
        {
            "position": "4",
            "constructor": "racing_point",
            "name": "Racing Point"
        },
        {
            "position": "5",
            "constructor": "renault",
            "name": "Renault"
        },
        {
            "position": "6",
            "constructor": "ferrari",
            "name": "Ferrari"
        },
        {
            "position": "7",
            "constructor": "alphatauri",
            "name": "AlphaTauri"
        },
        {
            "position": "8",
            "constructor": "alfa",
            "name": "Alfa Romeo"
        },
        {
            "position": "9",
            "constructor": "haas",
            "name": "Haas F1 Team"
        },
        {
            "position": "10",
            "constructor": "williams",
            "name": "Williams"
        }
    ],
    "16": [
        {
            "position": "1",
            "constructor": "mercedes",
            "name": "Mercedes"
        },
        {
            "position": "2",
            "constructor": "red_bull",
            "name": "Red Bull"
        },
        {
            "position": "3",
            "constructor": "racing_point",
            "name": "Racing Point"
        },
        {
            "position": "4",
            "constructor": "mclaren",
            "name": "McLaren"
        },
        {
            "position": "5",
            "constructor": "renault",
            "name": "Renault"
        },
        {
            "position": "6",
            "constructor": "ferrari",
            "name": "Ferrari"
        },
        {
            "position": "7",
            "constructor": "alphatauri",
            "name": "AlphaTauri"
        },
        {
            "position": "8",
            "constructor": "alfa",
            "name": "Alfa Romeo"
        },
        {
            "position": "9",
            "constructor": "haas",
            "name": "Haas F1 Team"
        },
        {
            "position": "10",
            "constructor": "williams",
            "name": "Williams"
        }
    ],
    "17": [
        {
            "position": "1",
            "constructor": "mercedes",
            "name": "Mercedes"
        },
        {
            "position": "2",
            "constructor": "red_bull",
            "name": "Red Bull"
        },
        {
            "position": "3",
            "constructor": "mclaren",
            "name": "McLaren"
        },
        {
            "position": "4",
            "constructor": "racing_point",
            "name": "Racing Point"
        },
        {
            "position": "5",
            "constructor": "renault",
            "name": "Renault"
        },
        {
            "position": "6",
            "constructor": "ferrari",
            "name": "Ferrari"
        },
        {
            "position": "7",
            "constructor": "alphatauri",
            "name": "AlphaTauri"
        },
        {
            "position": "8",
            "constructor": "alfa",
            "name": "Alfa Romeo"
        },
        {
            "position": "9",
            "constructor": "haas",
            "name": "Haas F1 Team"
        },
        {
            "position": "10",
            "constructor": "williams",
            "name": "Williams"
        }
    ]
}